Mealy_FSM.v
//This code is to detect the bit stream of 0110 using mealy FSM

module Mealy_FSM(Reset,Clock,x,z);
    input Reset,Clock,x;
    output reg z;
    reg [1:0] PS, NS;
    parameter S0=0,S1=1,S2=2,S3=3;

always @(posedge Clock or posedge Reset)
    if(Reset) PS<=S0;
    else PS<=NS;

always @(PS,x)
case(PS)
S0: begin
    z=0;
    NS=x?S0:S1;
end
S1: begin
    z=0;
    NS=x?S2:S1;
end
S2: begin
    z=0;
    NS=x?S3:S1;
end
S3: begin
    z=1;
    NS=x?S0:S1;
end
endcase
endmodule

Mealy_tb.v
//Test bench for Mealy FSM to detect 0110

`timescale 1ns/1ns
`include "Mealy_FSM.v"

module Mealy_tb;
reg Rst,Clk,x;
wire z;

Mealy_FSM DUT(Rst,Clk,x,z);

initial
begin
    $dumpfile("Mealy.vcd");
    $dumpvars(0,Mealy_tb);
    Clk=1'b0;
    Rst=1'b1;
    #15 Rst=1'b0;
end

always #5 Clk=~Clk;

initial
begin
    #12 x=1; #10 x=0; #10 x=0; #10 x=1;
    #10 x=0; #10 x=1; #10 x=1; #10 x=0;
    #10 x=1; #10 x=0; #10 x=0; #10 x=1;
    #10 $finish;
end
endmodule

Mealy.vcd
$date
	Sun Jul 09 15:37:58 2023
$end
$version
	Icarus Verilog
$end
$timescale
	1ns
$end
$scope module Mealy_tb $end
$var wire 1 ! z $end
$var reg 1 " Clk $end
$var reg 1 # Rst $end
$var reg 1 $ x $end
$scope module DUT $end
$var wire 1 " Clock $end
$var wire 1 # Reset $end
$var wire 1 $ x $end
$var parameter 32 % S0 $end
$var parameter 32 & S1 $end
$var parameter 32 ' S2 $end
$var parameter 32 ( S3 $end
$var reg 2 ) NS [1:0] $end
$var reg 2 * PS [1:0] $end
$var reg 1 ! z $end
$upscope $end
$upscope $end
$enddefinitions $end
$comment Show the parameter values. $end
$dumpall
b11 (
b10 '
b1 &
b0 %
$end
#0
$dumpvars
b0 *
b0x )
x$
1#
0"
0!
$end
#5
1"
#10
0"
#12
b0 )
1$
#15
1"
0#
#20
0"
#22
b1 )
0$
#25
b1 *
1"
#30
0"
#35
1"
#40
0"
#42
b10 )
1$
#45
b11 )
b10 *
1"
#50
0"
#52
b1 )
0$
#55
b1 *
1"
#60
0"
#62
b10 )
1$
#65
b11 )
b10 *
1"
#70
0"
#75
b0 )
1!
b11 *
1"
#80
0"
#82
b1 )
0$
#85
0!
b1 *
1"
#90
0"
#92
b10 )
1$
#95
b11 )
b10 *
1"
#100
0"
#102
b1 )
0$
#105
b1 *
1"
#110
0"
#115
1"
#120
0"
#122
b10 )
1$
#125
b11 )
b10 *
1"
