Moore_FSM.v
//This code is written for the sequence detection of 101101
module Moore_FSM(Reset, Clock, x,z);
    input Reset, Clock, x;
    output reg z;
    parameter S0=0,S1=1,S2=2,S3=3,S4=4,S5=5,S6=6; //to show different state transistions
    reg [2:0] PS,NS; //present and next state variables

always @(posedge Clock or posedge Reset) //this always block is to store the state information
    if(Reset) PS<=S0; //if reset is active then remain at  state 0
    else PS<= NS;//if reset is not active then go to next state

always@(PS,x) //this always block is for stransition between states depending upon PS & PI
    case(PS) //PS=present state, PI=present input
    S0:begin
        z=0;
        NS=x?S1:S0;
    end
    S1:begin
        z=0;
        NS=x?S1:S2;
    end
    S2:begin
        z=0;
        NS=x?S3:S0;
    end
    S3:begin
        z=0;
        NS=x?S4:S2;
    end
    S4:begin
        z=0;
        NS=x?S1:S5;
    end
    S5:begin
        z=0;
        NS=x?S6:S0;
    end
    S6:begin
        z=1;
        NS=x?S1:S2;
    end
endcase
endmodule

Moore_tb.v
//test bench for detection of 101101 using Moore FSM

`timescale 1ns/1ns
`include "Moore_FSM.v"

module Moore_tb;
reg Rst,Clk,x;
wire z;

Moore_FSM DUT(Rst,Clk,x,z);

initial begin
    $dumpfile("Moore_tb.vcd");
    $dumpvars(0,Moore_tb);
    Clk=1'b0;
    Rst=1'b1;
    #15 Rst=1'b0; //reset active after 15 sec
end

always #5 Clk = ~Clk;

initial begin
    #12 x=0; #10 x=1; #10 x=0; #10 x=1;
    #12 x=1; #10 x=0; #10 x=1; #10 x=0;
    #12 x=0; #10 x=1; #10 x=0; #10 x=1;
    #10 $finish;
end
endmodule

Moore_tb.vcd
$date
	Sun Jul 09 13:43:31 2023
$end
$version
	Icarus Verilog
$end
$timescale
	1ns
$end
$scope module Moore_tb $end
$var wire 1 ! z $end
$var reg 1 " Clk $end
$var reg 1 # Rst $end
$var reg 1 $ x $end
$scope module DUT $end
$var wire 1 " Clock $end
$var wire 1 # Reset $end
$var wire 1 $ x $end
$var parameter 32 % S0 $end
$var parameter 32 & S1 $end
$var parameter 32 ' S2 $end
$var parameter 32 ( S3 $end
$var parameter 32 ) S4 $end
$var parameter 32 * S5 $end
$var parameter 32 + S6 $end
$var reg 3 , NS [2:0] $end
$var reg 3 - PS [2:0] $end
$var reg 1 ! z $end
$upscope $end
$upscope $end
$enddefinitions $end
$comment Show the parameter values. $end
$dumpall
b110 +
b101 *
b100 )
b11 (
b10 '
b1 &
b0 %
$end
#0
$dumpvars
b0 -
b0x ,
x$
1#
0"
0!
$end
#5
1"
#10
0"
#12
b0 ,
0$
#15
1"
0#
#20
0"
#22
b1 ,
1$
#25
b1 -
1"
#30
0"
#32
b10 ,
0$
#35
b0 ,
b10 -
1"
#40
0"
#42
b11 ,
1$
#45
b100 ,
b11 -
1"
#50
0"
#55
b1 ,
b100 -
1"
#60
0"
#64
b101 ,
0$
#65
b0 ,
b101 -
1"
#70
0"
#74
b110 ,
1$
#75
b1 ,
1!
b110 -
1"
#80
0"
#84
b10 ,
0$
#85
b0 ,
0!
b10 -
1"
#90
0"
#95
b0 -
1"
#100
0"
#105
1"
#106
b1 ,
1$
#110
0"
#115
b1 -
1"
#116
b10 ,
0$
#120
0"
#125
b0 ,
b10 -
1"
#126
b11 ,
1$
#130
0"
#135
b100 ,
b11 -
1"
